pybrokk/__init__.py
pybrokk/bow.py
pybrokk/create_id.py
pybrokk/duster.py
pybrokk/pybrokk.py
pybrokk/text_from_url.py
pybrokk-0.0.10.dist-info/METADATA
pybrokk-0.0.10.dist-info/WHEEL
pybrokk-0.0.10.dist-info/LICENSE
pybrokk-0.0.10.dist-info/RECORD
