Metadata-Version: 2.1
Name: pybrokk
Version: 0.0.10
Summary: A package that takes a list of URLs and creates a dataframe for machine learning projects using  BOW
License: MIT
Author: Elena Ganacheva, Mehdi Naji, Mike Guron, Daniel Merigo
Requires-Python: >=3.9,<4.0
Classifier: License :: OSI Approved :: MIT License
Classifier: Programming Language :: Python :: 3
Classifier: Programming Language :: Python :: 3.9
Classifier: Programming Language :: Python :: 3.10
Classifier: Programming Language :: Python :: 3.11
Requires-Dist: beautifulsoup4 (>=4.11.1,<5.0.0)
Requires-Dist: pandas (>=1.5.2,<2.0.0)
Requires-Dist: requests (>=2.28.2,<3.0.0)
Requires-Dist: scikit-learn (>=1.2.0,<2.0.0)
